avchd_toolkit-0.4.2.dist-info/DESCRIPTION.rst
avchd_toolkit-0.4.2.dist-info/METADATA
avchd_toolkit-0.4.2.dist-info/RECORD
avchd_toolkit-0.4.2.dist-info/WHEEL
avchd_toolkit-0.4.2.dist-info/entry_points.txt
avchd_toolkit-0.4.2.dist-info/metadata.json
avchd_toolkit-0.4.2.dist-info/top_level.txt
avchd_toolkit-0.4.2.dist-info/zip-safe
avchdrenamer/__init__.py
avchdrenamer/cmdline.py
avchdrenamer/rename.py
avchdtoolkit/__init__.py
avchdtoolkit/archive.py
avchdtoolkit/codecs.ini
avchdtoolkit/conversion.py
avchdtoolkit/exiftool.py
avchdtoolkit/ffmpeg.py
avchdtoolkit/finder.py
avchdtoolkit/metadata.py
avchdtoolkit/profiles.py
avchdtoolkit/renamer.py
avchdtoolkit/timecode.py
avchdtoolkit/commands/__init__.py
avchdtoolkit/commands/archive.py
avchdtoolkit/commands/extract_timecodes.py
avchdtoolkit/commands/rename.py
avchdtoolkit/commands/transcode.py
avchdtrans/__init__.py
avchdtrans/cmdline.py
avchdtrans/codecs.ini
avchdtrans/conversion.py
avchdtrans/exiftool.py
avchdtrans/ffmpeg.py
avchdtrans/finder.py
avchdtrans/metadata.py
avchdtrans/profiles.py
avchdtrans/timecode.py
avchdtrans/commands/__init__.py
avchdtrans/commands/extract_timecodes.py
